ttscorpus/__init__.py
ttscorpus/source/__init__.py
ttscorpus/source/android_tts.py
ttscorpus/source/google_cloud.py
ttscorpus/source/google_tts.py
ttscorpus/source/mac.py
ttscorpus-0.0.2.dist-info/METADATA
ttscorpus-0.0.2.dist-info/WHEEL
ttscorpus-0.0.2.dist-info/top_level.txt
ttscorpus-0.0.2.dist-info/RECORD
