Metadata-Version: 2.1
Name: ttscorpus
Version: 0.0.2
Summary: collection of different source of tts api for generating corpus.
Home-page: https://github.com/voidful/tts-corpus-creator
Author: Voidful
Author-email: voidful.stack@gmail.com
License: Apache
Keywords: tts google tts gtts mac android tts
Platform: UNKNOWN
Classifier: Development Status :: 4 - Beta
Classifier: Intended Audience :: Science/Research
Classifier: Topic :: Scientific/Engineering :: Artificial Intelligence
Classifier: License :: OSI Approved :: Apache Software License
Classifier: Programming Language :: Python :: 3.6
Requires-Python: >=3.5.0
